PM_Elib/Funciones.py
PM_Elib/Pruebas.py
PM_Elib/__init__.py
PM_Elib-0.0.1.dist-info/METADATA
PM_Elib-0.0.1.dist-info/WHEEL
PM_Elib-0.0.1.dist-info/top_level.txt
PM_Elib-0.0.1.dist-info/RECORD
