Metadata-Version: 2.1
Name: PM-Elib
Version: 0.0.1
Summary: Librería para realizar mineria de procesos a partir de un archivo .CSV
Home-page: https://github.com/edraalfig
Author: Edwin Alfaro Iguarán
Author-email: edraalfig@gmail.com
License: MIT
Requires-Dist: numpy
Requires-Dist: pandas
